web_proxy/__init__.py
web_proxy/__log.py
web_proxy/proxy.py
web_proxy-0.1.3.dist-info/METADATA
web_proxy-0.1.3.dist-info/WHEEL
web_proxy-0.1.3.dist-info/RECORD
