Metadata-Version: 2.1
Name: web-proxy
Version: 0.1.3
Summary: Use web proxy website to proxy http clients such as urllib or requests
Author: zyg
Author-email: jawide@qq.com
Requires-Python: >=3.7,<4.0
Classifier: Programming Language :: Python :: 3
Classifier: Programming Language :: Python :: 3.7
Classifier: Programming Language :: Python :: 3.8
Classifier: Programming Language :: Python :: 3.9
Classifier: Programming Language :: Python :: 3.10
Classifier: Programming Language :: Python :: 3.11
